tspydistributions/__init__.py
tspydistributions/api.py
tspydistributions/density.py
tspydistributions/estimation.py
tspydistributions/helpers.py
tspydistributions/numderiv.py
tspydistributions/pdqr.py
tspydistributions/plot.py
tspydistributions/profiling.py
tspydistributions/sandwich.py
tspydistributions-0.1.3.dist-info/LICENSE
tspydistributions-0.1.3.dist-info/METADATA
tspydistributions-0.1.3.dist-info/WHEEL
tspydistributions-0.1.3.dist-info/RECORD
