Metadata-Version: 2.1
Name: tspydistributions
Version: 0.1.3
Summary: Location Scale Family Statistical Distributions
Home-page: https://github.com/tsmodelspy/tspydistributions
License: MIT
Author: Alexios Galanos
Author-email: alexios@4dscape.com
Requires-Python: >=3.10,<3.13
Classifier: License :: OSI Approved :: MIT License
Classifier: Programming Language :: Python :: 3
Classifier: Programming Language :: Python :: 3.10
Classifier: Programming Language :: Python :: 3.11
Classifier: Programming Language :: Python :: 3.12
Requires-Dist: jaxtyping (>=0.2.25,<0.3.0)
Requires-Dist: numdifftools (>=0.9.41,<0.10.0)
Requires-Dist: numpy (>=1.25.2,<2.0.0)
Requires-Dist: pandas (>=2.1.3,<3.0.0)
Requires-Dist: plotnine (>=0.12.4,<0.13.0)
Requires-Dist: scipy (>=1.11.2,<2.0.0)
Requires-Dist: setuptools (>=69.0.2,<70.0.0)
Requires-Dist: tabulate (>=0.9.0,<0.10.0)
Requires-Dist: torch (>=2.1.1,<3.0.0)
Project-URL: Documentation, https://tspydistributions.readthedocs.io/en/latest/
Project-URL: Repository, https://github.com/tsmodelspy/tspydistributions
